{
    "frames": [
        {
            "filename": "hearts_6",
            "frame": {
                "w": 500,
                "h": 726,
                "x": 0,
                "y": 0
            },
            "anchor": {
                "x": 0.5,
                "y": 0.5
            }
        },
        {
            "filename": "clubs_7",
            "frame": {
                "w": 500,
                "h": 726,
                "x": 500,
                "y": 0
            },
            "anchor": {
                "x": 0.5,
                "y": 0.5
            }
        },
        {
            "filename": "spades_6",
            "frame": {
                "w": 500,
                "h": 726,
                "x": 0,
                "y": 726
            },
            "anchor": {
                "x": 0.5,
                "y": 0.5
            }
        },
        {
            "filename": "diamond_7",
            "frame": {
                "w": 500,
                "h": 726,
                "x": 500,
                "y": 726
            },
            "anchor": {
                "x": 0.5,
                "y": 0.5
            }
        },
        {
            "filename": "hearts_7",
            "frame": {
                "w": 500,
                "h": 726,
                "x": 1000,
                "y": 0
            },
            "anchor": {
                "x": 0.5,
                "y": 0.5
            }
        },
        {
            "filename": "spades_7",
            "frame": {
                "w": 500,
                "h": 726,
                "x": 1000,
                "y": 726
            },
            "anchor": {
                "x": 0.5,
                "y": 0.5
            }
        },
        {
            "filename": "clubs_8",
            "frame": {
                "w": 500,
                "h": 726,
                "x": 0,
                "y": 1452
            },
            "anchor": {
                "x": 0.5,
                "y": 0.5
            }
        },
        {
            "filename": "diamond_8",
            "frame": {
                "w": 500,
                "h": 726,
                "x": 500,
                "y": 1452
            },
            "anchor": {
                "x": 0.5,
                "y": 0.5
            }
        },
        {
            "filename": "hearts_8",
            "frame": {
                "w": 500,
                "h": 726,
                "x": 1000,
                "y": 1452
            },
            "anchor": {
                "x": 0.5,
                "y": 0.5
            }
        },
        {
            "filename": "spades_8",
            "frame": {
                "w": 500,
                "h": 726,
                "x": 1500,
                "y": 0
            },
            "anchor": {
                "x": 0.5,
                "y": 0.5
            }
        },
        {
            "filename": "clubs_9",
            "frame": {
                "w": 500,
                "h": 726,
                "x": 1500,
                "y": 726
            },
            "anchor": {
                "x": 0.5,
                "y": 0.5
            }
        },
        {
            "filename": "diamond_9",
            "frame": {
                "w": 500,
                "h": 726,
                "x": 1500,
                "y": 1452
            },
            "anchor": {
                "x": 0.5,
                "y": 0.5
            }
        },
        {
            "filename": "hearts_9",
            "frame": {
                "w": 500,
                "h": 726,
                "x": 2000,
                "y": 0
            },
            "anchor": {
                "x": 0.5,
                "y": 0.5
            }
        },
        {
            "filename": "spades_9",
            "frame": {
                "w": 500,
                "h": 726,
                "x": 2000,
                "y": 726
            },
            "anchor": {
                "x": 0.5,
                "y": 0.5
            }
        },
        {
            "filename": "clubs_10",
            "frame": {
                "w": 500,
                "h": 726,
                "x": 2000,
                "y": 1452
            },
            "anchor": {
                "x": 0.5,
                "y": 0.5
            }
        },
        {
            "filename": "diamond_10",
            "frame": {
                "w": 500,
                "h": 726,
                "x": 0,
                "y": 2178
            },
            "anchor": {
                "x": 0.5,
                "y": 0.5
            }
        },
        {
            "filename": "hearts_10",
            "frame": {
                "w": 500,
                "h": 726,
                "x": 500,
                "y": 2178
            },
            "anchor": {
                "x": 0.5,
                "y": 0.5
            }
        },
        {
            "filename": "spades_10",
            "frame": {
                "w": 500,
                "h": 726,
                "x": 1000,
                "y": 2178
            },
            "anchor": {
                "x": 0.5,
                "y": 0.5
            }
        },
        {
            "filename": "clubs_1",
            "frame": {
                "w": 500,
                "h": 726,
                "x": 1500,
                "y": 2178
            },
            "anchor": {
                "x": 0.5,
                "y": 0.5
            }
        },
        {
            "filename": "diamond_1",
            "frame": {
                "w": 500,
                "h": 726,
                "x": 2000,
                "y": 2178
            },
            "anchor": {
                "x": 0.5,
                "y": 0.5
            }
        },
        {
            "filename": "hearts_1",
            "frame": {
                "w": 500,
                "h": 726,
                "x": 2500,
                "y": 0
            },
            "anchor": {
                "x": 0.5,
                "y": 0.5
            }
        },
        {
            "filename": "spades_1",
            "frame": {
                "w": 500,
                "h": 726,
                "x": 2500,
                "y": 726
            },
            "anchor": {
                "x": 0.5,
                "y": 0.5
            }
        },
        {
            "filename": "clubs_11",
            "frame": {
                "w": 500,
                "h": 726,
                "x": 0,
                "y": 2904
            },
            "anchor": {
                "x": 0.5,
                "y": 0.5
            }
        },
        {
            "filename": "diamond_11",
            "frame": {
                "w": 500,
                "h": 726,
                "x": 500,
                "y": 2904
            },
            "anchor": {
                "x": 0.5,
                "y": 0.5
            }
        },
        {
            "filename": "hearts_11",
            "frame": {
                "w": 500,
                "h": 726,
                "x": 1000,
                "y": 2904
            },
            "anchor": {
                "x": 0.5,
                "y": 0.5
            }
        },
        {
            "filename": "clubs_13",
            "frame": {
                "w": 500,
                "h": 726,
                "x": 1500,
                "y": 2904
            },
            "anchor": {
                "x": 0.5,
                "y": 0.5
            }
        },
        {
            "filename": "hearts_13",
            "frame": {
                "w": 500,
                "h": 726,
                "x": 2000,
                "y": 2904
            },
            "anchor": {
                "x": 0.5,
                "y": 0.5
            }
        },
        {
            "filename": "diamond_13",
            "frame": {
                "w": 500,
                "h": 726,
                "x": 2500,
                "y": 2904
            },
            "anchor": {
                "x": 0.5,
                "y": 0.5
            }
        },
        {
            "filename": "spades_13",
            "frame": {
                "w": 500,
                "h": 726,
                "x": 3000,
                "y": 0
            },
            "anchor": {
                "x": 0.5,
                "y": 0.5
            }
        },
        {
            "filename": "clubs_12",
            "frame": {
                "w": 500,
                "h": 726,
                "x": 3000,
                "y": 726
            },
            "anchor": {
                "x": 0.5,
                "y": 0.5
            }
        },
        {
            "filename": "diamond_12",
            "frame": {
                "w": 500,
                "h": 726,
                "x": 3000,
                "y": 1452
            },
            "anchor": {
                "x": 0.5,
                "y": 0.5
            }
        },
        {
            "filename": "hearts_12",
            "frame": {
                "w": 500,
                "h": 726,
                "x": 3000,
                "y": 2178
            },
            "anchor": {
                "x": 0.5,
                "y": 0.5
            }
        },
        {
            "filename": "spades_12",
            "frame": {
                "w": 500,
                "h": 726,
                "x": 3000,
                "y": 2904
            },
            "anchor": {
                "x": 0.5,
                "y": 0.5
            }
        },
        {
            "filename": "diamond_2",
            "frame": {
                "w": 500,
                "h": 726,
                "x": 3500,
                "y": 726
            },
            "anchor": {
                "x": 0.5,
                "y": 0.5
            }
        },
        {
            "filename": "spades_11",
            "frame": {
                "w": 500,
                "h": 726,
                "x": 3500,
                "y": 1452
            },
            "anchor": {
                "x": 0.5,
                "y": 0.5
            }
        },
        {
            "filename": "spades_2",
            "frame": {
                "w": 500,
                "h": 726,
                "x": 3500,
                "y": 2178
            },
            "anchor": {
                "x": 0.5,
                "y": 0.5
            }
        },
        {
            "filename": "clubs_3",
            "frame": {
                "w": 500,
                "h": 726,
                "x": 3500,
                "y": 2904
            },
            "anchor": {
                "x": 0.5,
                "y": 0.5
            }
        },
        {
            "filename": "diamond_3",
            "frame": {
                "w": 500,
                "h": 726,
                "x": 0,
                "y": 3630
            },
            "anchor": {
                "x": 0.5,
                "y": 0.5
            }
        },
        {
            "filename": "hearts_3",
            "frame": {
                "w": 500,
                "h": 726,
                "x": 500,
                "y": 3630
            },
            "anchor": {
                "x": 0.5,
                "y": 0.5
            }
        },
        {
            "filename": "diamond_4",
            "frame": {
                "w": 500,
                "h": 726,
                "x": 1000,
                "y": 3630
            },
            "anchor": {
                "x": 0.5,
                "y": 0.5
            }
        },
        {
            "filename": "diamond_5",
            "frame": {
                "w": 500,
                "h": 726,
                "x": 1500,
                "y": 3630
            },
            "anchor": {
                "x": 0.5,
                "y": 0.5
            }
        },
        {
            "filename": "clubs_5",
            "frame": {
                "w": 500,
                "h": 726,
                "x": 2000,
                "y": 3630
            },
            "anchor": {
                "x": 0.5,
                "y": 0.5
            }
        },
        {
            "filename": "spades_5",
            "frame": {
                "w": 500,
                "h": 726,
                "x": 2500,
                "y": 3630
            },
            "anchor": {
                "x": 0.5,
                "y": 0.5
            }
        },
        {
            "filename": "hearts_5",
            "frame": {
                "w": 500,
                "h": 726,
                "x": 3000,
                "y": 3630
            },
            "anchor": {
                "x": 0.5,
                "y": 0.5
            }
        },
        {
            "filename": "clubs_2",
            "frame": {
                "w": 500,
                "h": 726,
                "x": 3500,
                "y": 3630
            },
            "anchor": {
                "x": 0.5,
                "y": 0.5
            }
        },
        {
            "filename": "spades_4",
            "frame": {
                "w": 500,
                "h": 726,
                "x": 4000,
                "y": 0
            },
            "anchor": {
                "x": 0.5,
                "y": 0.5
            }
        },
        {
            "filename": "spades_3",
            "frame": {
                "w": 500,
                "h": 726,
                "x": 4000,
                "y": 726
            },
            "anchor": {
                "x": 0.5,
                "y": 0.5
            }
        },
        {
            "filename": "clubs_4",
            "frame": {
                "w": 500,
                "h": 726,
                "x": 4000,
                "y": 1452
            },
            "anchor": {
                "x": 0.5,
                "y": 0.5
            }
        },
        {
            "filename": "hearts_2",
            "frame": {
                "w": 500,
                "h": 726,
                "x": 4000,
                "y": 2178
            },
            "anchor": {
                "x": 0.5,
                "y": 0.5
            }
        },
        {
            "filename": "clubs_6",
            "frame": {
                "w": 500,
                "h": 726,
                "x": 4000,
                "y": 2904
            },
            "anchor": {
                "x": 0.5,
                "y": 0.5
            }
        },
        {
            "filename": "hearts_4",
            "frame": {
                "w": 500,
                "h": 726,
                "x": 4000,
                "y": 3630
            },
            "anchor": {
                "x": 0.5,
                "y": 0.5
            }
        },
        {
            "filename": "diamond_6",
            "frame": {
                "w": 500,
                "h": 726,
                "x": 0,
                "y": 4356
            },
            "anchor": {
                "x": 0.5,
                "y": 0.5
            }
        },
      

    ],
    "meta": {
        "description": "Atlas generado con Atlas Packer Gamma V2",
        "web": "https://gammafp.github.io/atlas-packer-phaser/"
    }
}